{
      "notes": [
        {
          "name": "A0",
          "midi": 21,
          "time": 2.5624999999999999,
          "velocity": 0.7874015748031497,
          "duration": 2.41875
        },
        {
          "name": "A0",
          "midi": 21,
          "time": 3.58125,
          "velocity": 0.7874015748031497,
          "duration": 2.4000000000000004
        },
        {
          "name": "A0",
          "midi": 21,
          "time": 5.9625,
          "velocity": 0.7874015748031497,
          "duration": 2.4000000000000004
        },
        {
          "name": "A0",
          "midi": 21,
          "time": 8.3625,
          "velocity": 0.7874015748031497,
          "duration": 4.837499999999999
        },
        {
          "name": "E0",
          "midi": 16,
          "time": 13.212499999999999,
          "velocity": 0.7874015748031497,
          "duration": 2.4000000000000004
        },
        {
          "name": "A0",
          "midi": 21,
          "time": 15.562499999999998,
          "velocity": 0.7874015748031497,
          "duration": 2.418750000000001
        },
        {
          "name": "E0",
          "midi": 16,
          "time": 17.98125,
          "velocity": 0.7874015748031497,
          "duration": 1.1812499999999986
        }
      ]
}